{
  "Unknown": {
    "ch120a": [
      {
        "Code": "8.1",
        "Strand": "School districts and open-enrollment charter schools are required to provide instruction in the",
        "Expectations": []
      },
      {
        "Code": "8.2",
        "Strand": "School districts may provide the required instruction in a variety of arrangements, including",
        "Expectations": []
      },
      {
        "Code": "8.1",
        "Strand": "Character education introduces students to character traits and personal skills that empower them",
        "Expectations": []
      },
      {
        "Code": "8.2",
        "Strand": "The standards for positive character traits and personal skills are comprised of four strands:",
        "Expectations": []
      },
      {
        "Code": "8.3",
        "Strand": "Students are expected to develop an awareness of self-identity as well as recognize multiple",
        "Expectations": []
      },
      {
        "Code": "8.4",
        "Strand": "The knowledge and skills for positive character traits and personal skills are organized in the",
        "Expectations": []
      },
      {
        "Code": "8.5",
        "Strand": "Statements that contain the word \"including\" reference content that must be mastered, while those",
        "Expectations": []
      },
      {
        "Code": "8.1",
        "Strand": "Trustworthiness. The student understands how personal skills, choices, and actions relate to",
        "Expectations": []
      },
      {
        "Code": "8.2",
        "Strand": "Responsibility. The student understands the concept of responsibility and how personal actions",
        "Expectations": []
      },
      {
        "Code": "8.3",
        "Strand": "Caring. The student understands how personal actions and interpersonal skills demonstrate",
        "Expectations": []
      },
      {
        "Code": "8.4",
        "Strand": "Good citizenship. The student understands how personal actions and responsible decision making",
        "Expectations": []
      },
      {
        "Code": "8.1",
        "Strand": "School districts and open-enrollment charter schools are required to provide instruction in the",
        "Expectations": []
      },
      {
        "Code": "8.2",
        "Strand": "School districts may provide the required instruction in a variety of arrangements, including",
        "Expectations": []
      },
      {
        "Code": "8.1",
        "Strand": "Character education introduces students to character traits and personal skills that empower them",
        "Expectations": []
      },
      {
        "Code": "8.2",
        "Strand": "The standards for positive character traits and personal skills are comprised of four strands:",
        "Expectations": []
      },
      {
        "Code": "8.3",
        "Strand": "Students are expected to develop an awareness of self-identity as well as recognize multiple",
        "Expectations": []
      },
      {
        "Code": "8.4",
        "Strand": "The knowledge and skills for positive character traits and personal skills are organized in the",
        "Expectations": []
      },
      {
        "Code": "8.5",
        "Strand": "Statements that contain the word \"including\" reference content that must be mastered, while those",
        "Expectations": []
      },
      {
        "Code": "8.1",
        "Strand": "Trustworthiness. The student understands how personal skills, choices, and actions build",
        "Expectations": []
      },
      {
        "Code": "8.2",
        "Strand": "Responsibility. The student understands how personal choices are associated with responsibility.",
        "Expectations": []
      },
      {
        "Code": "8.3",
        "Strand": "Caring. The student understands how personal actions and interpersonal skills demonstrate",
        "Expectations": []
      },
      {
        "Code": "8.4",
        "Strand": "Good citizenship. The student understands that personal responsibility and responsible decision",
        "Expectations": []
      },
      {
        "Code": "8.1",
        "Strand": "School districts and open-enrollment charter schools are required to provide instruction in the",
        "Expectations": []
      },
      {
        "Code": "8.2",
        "Strand": "School districts may provide the required instruction in a variety of arrangements, including",
        "Expectations": []
      },
      {
        "Code": "8.1",
        "Strand": "Character education introduces students to character traits and personal skills that empower them",
        "Expectations": []
      },
      {
        "Code": "8.2",
        "Strand": "The standards for positive character traits and personal skills are comprised of four strands:",
        "Expectations": []
      },
      {
        "Code": "8.3",
        "Strand": "Students are expected to develop an awareness of self-identity as well as recognize multiple",
        "Expectations": []
      },
      {
        "Code": "8.4",
        "Strand": "The knowledge and skills for positive character traits and personal skills are organized in the",
        "Expectations": []
      },
      {
        "Code": "8.5",
        "Strand": "Statements that contain the word \"including\" reference content that must be mastered, while those",
        "Expectations": []
      },
      {
        "Code": "8.1",
        "Strand": "Trustworthiness. The student understands how personal skills, choices, and actions build",
        "Expectations": []
      },
      {
        "Code": "8.2",
        "Strand": "Responsibility. The student understands how personal beliefs and feelings and self-management",
        "Expectations": []
      },
      {
        "Code": "8.3",
        "Strand": "Caring. The student understands how interpersonal skills and characteristics of caring impact",
        "Expectations": []
      },
      {
        "Code": "8.4",
        "Strand": "Good citizenship. The student understands how responsible decision making and good citizenship",
        "Expectations": []
      },
      {
        "Code": "8.1",
        "Strand": "School districts and open-enrollment charter schools are required to provide instruction in the",
        "Expectations": []
      },
      {
        "Code": "8.2",
        "Strand": "School districts may provide the required instruction in a variety of arrangements, including",
        "Expectations": []
      },
      {
        "Code": "8.1",
        "Strand": "Character education introduces students to character traits and personal skills that empower them",
        "Expectations": []
      },
      {
        "Code": "8.2",
        "Strand": "The standards for positive character traits and personal skills are comprised of four strands:",
        "Expectations": []
      },
      {
        "Code": "8.3",
        "Strand": "Students are expected to develop an awareness of self-identity as well as recognize multiple",
        "Expectations": []
      },
      {
        "Code": "8.4",
        "Strand": "The knowledge and skills for positive character traits and personal skills are organized in the",
        "Expectations": []
      },
      {
        "Code": "8.5",
        "Strand": "Statements that contain the word \"including\" reference content that must be mastered, while those",
        "Expectations": []
      },
      {
        "Code": "8.1",
        "Strand": "Trustworthiness. The student understands how trustworthiness is viewed in society, politics, and",
        "Expectations": []
      },
      {
        "Code": "8.2",
        "Strand": "Responsibility. The student understands how leaders demonstrate responsibility in relationships,",
        "Expectations": []
      },
      {
        "Code": "8.3",
        "Strand": "Caring. The student understands how interpersonal skills and characteristics of caring influence",
        "Expectations": []
      },
      {
        "Code": "8.4",
        "Strand": "Good citizenship. The student understands how responsible decision making and good citizenship",
        "Expectations": []
      }
    ]
  }
}